genie.libs.parser-24.6-py3.11-nspkg.pth
genie/libs/parser/__init__.py
genie/libs/parser/base.py
genie/libs/parser/parsers.json
genie/libs/parser/aireos/__init__.py
genie/libs/parser/aireos/ping.py
genie/libs/parser/aireos/show_boot.py
genie/libs/parser/apic/__init__.py
genie/libs/parser/apic/acidiag.py
genie/libs/parser/apic/df.py
genie/libs/parser/apic/fnvread.py
genie/libs/parser/apic/ls.py
genie/libs/parser/apic/show_firmware.py
genie/libs/parser/apic/show_platform.py
genie/libs/parser/asa/__init__.py
genie/libs/parser/asa/show_arp.py
genie/libs/parser/asa/show_asp.py
genie/libs/parser/asa/show_context.py
genie/libs/parser/asa/show_crypto_ikev2_sa.py
genie/libs/parser/asa/show_failover.py
genie/libs/parser/asa/show_interface.py
genie/libs/parser/asa/show_inventory.py
genie/libs/parser/asa/show_ip.py
genie/libs/parser/asa/show_nameif.py
genie/libs/parser/asa/show_resource.py
genie/libs/parser/asa/show_route.py
genie/libs/parser/asa/show_service_policy.py
genie/libs/parser/asa/show_traffic.py
genie/libs/parser/asa/show_version.py
genie/libs/parser/asa/show_vpn.py
genie/libs/parser/asa/show_vpn_sessiondb.py
genie/libs/parser/asa/tests/__init__.py
genie/libs/parser/bigip/__init__.py
genie/libs/parser/bigip/get_access_acl_stats.py
genie/libs/parser/bigip/get_access_bundle_install_tasks.py
genie/libs/parser/bigip/get_access_profile_access_misc_stats.py
genie/libs/parser/bigip/get_access_profile_rewrite_stats.py
genie/libs/parser/bigip/get_access_profile_rewritestats.py
genie/libs/parser/bigip/get_access_redeploy_iapp_tasks.py
genie/libs/parser/bigip/get_access_sessionkill_sessions.py
genie/libs/parser/bigip/get_access_usecase_pack_info.py
genie/libs/parser/bigip/get_adc_fileobjectssl_cert.py
genie/libs/parser/bigip/get_adc_fileobjectssl_crl.py
genie/libs/parser/bigip/get_adc_fileobjectssl_csr.py
genie/libs/parser/bigip/get_adc_fileobjectssl_key.py
genie/libs/parser/bigip/get_analytics_afm_sweepergenerate_report.py
genie.libs.parser-24.6.dist-info/LICENSE
genie.libs.parser-24.6.dist-info/METADATA
genie.libs.parser-24.6.dist-info/WHEEL
genie.libs.parser-24.6.dist-info/namespace_packages.txt
genie.libs.parser-24.6.dist-info/top_level.txt
genie.libs.parser-24.6.dist-info/RECORD
