Metadata-Version: 2.1
Name: genie.libs.parser
Version: 24.6
Summary: Genie libs Parser: Genie Parser Libraries
Home-page: https://developer.cisco.com/pyats
Author: Cisco Systems Inc.
Author-email: pyats-support-ext@cisco.com
License: Apache 2.0
Keywords: genie pyats test automation
Classifier: Development Status :: 6 - Mature
Classifier: Development Status :: 5 - Production/Stable
Classifier: Environment :: Console
Classifier: Intended Audience :: Developers
Classifier: Intended Audience :: Telecommunications Industry
Classifier: Intended Audience :: Information Technology
Classifier: Intended Audience :: System Administrators
Classifier: License :: OSI Approved :: Apache Software License
Classifier: Operating System :: MacOS
Classifier: Operating System :: POSIX :: Linux
Classifier: Programming Language :: Python :: 3.7
Classifier: Programming Language :: Python :: 3.6
Classifier: Programming Language :: Python :: 3.5
Classifier: Programming Language :: Python :: 3 :: Only
Classifier: Programming Language :: Python :: Implementation :: CPython
Classifier: Topic :: Software Development :: Testing
Classifier: Topic :: Software Development :: Build Tools
Classifier: Topic :: Software Development :: Libraries
Classifier: Topic :: Software Development :: Libraries :: Python Modules
License-File: LICENSE
Requires-Dist: xmltodict
Provides-Extra: dev
Requires-Dist: coverage ; extra == 'dev'
Requires-Dist: restview ; extra == 'dev'
Requires-Dist: Sphinx ; extra == 'dev'
Requires-Dist: sphinx-rtd-theme ; extra == 'dev'
